rgbcolors/__init__.py
rgbcolors-3.0.0.dist-info/METADATA
rgbcolors-3.0.0.dist-info/RECORD
rgbcolors-3.0.0.dist-info/WHEEL
rgbcolors-3.0.0.dist-info/top_level.txt
