Metadata-Version: 2.1
Name: rgbcolors
Version: 3.0.0
Summary: RGB Colors
Home-page: https://github.com/pypa/sampleproject
Author: Bandi B
Author-email: laandro3@gmail.com
License: UNKNOWN
Platform: UNKNOWN
Classifier: Programming Language :: Python :: 3
Classifier: License :: OSI Approved :: MIT License
Classifier: Operating System :: OS Independent
